rmrag/__init__.py
rmrag/pipelines/__init__.py
rmrag/pipelines/directory_into_faiss.py
rmrag/pipelines/get_response_openai.py
rmrag/pipelines/get_response_opensource.py
rmrag/text_processing/__init__.py
rmrag/text_processing/load_files_from_directory.py
rmrag/text_processing/split_files.py
rmrag/text_processing/split_files_final_content.py
rmrag/vectorstores/__init__.py
rmrag/vectorstores/create_embeddings_and_faiss_vectorstore.py
rmrag/vectorstores/load_faiss_vectorstore.py
rmrag-0.4.dist-info/METADATA
rmrag-0.4.dist-info/WHEEL
rmrag-0.4.dist-info/top_level.txt
rmrag-0.4.dist-info/RECORD
