Metadata-Version: 2.1
Name: rmrag
Version: 0.4
Summary: RAG functions
Author: Lasse Tranekjær Leed
Author-email: lasseleed@gmail.com
Classifier: Development Status :: 3 - Alpha
Classifier: Intended Audience :: Developers
Classifier: Programming Language :: Python :: 3.9
